lzo.cpython-38-darwin.so
python_lzo-1.15.dist-info/COPYING
python_lzo-1.15.dist-info/METADATA
python_lzo-1.15.dist-info/WHEEL
python_lzo-1.15.dist-info/top_level.txt
python_lzo-1.15.dist-info/RECORD
