Metadata-Version: 2.1
Name: python-lzo
Version: 1.15
Summary: Python bindings for the LZO data compression library
Home-page: https://github.com/jd-boyd/python-lzo
Author: Markus F.X.J. Oberhumer
Author-email: markus@oberhumer.com
Maintainer: Joshua D. Boyd
Maintainer-email: jdboyd@jdboyd.net
License: GNU General Public License (GPL)
Platform: All
